mkdocs_mpgtheme_plugin/plugin.py
mkdocs_mpgtheme_plugin/assets/mpgtheme/css/mpg.css
mkdocs_mpgtheme_plugin/assets/mpgtheme/images/footer-logo-placeholder.svg
mkdocs_mpgtheme_plugin/assets/mpgtheme/images/footer-logo-placeholder.svg.license
mkdocs_mpgtheme_plugin/assets/mpgtheme/images/header-logo-bg.svg
mkdocs_mpgtheme_plugin/assets/mpgtheme/images/header-logo-bg.svg.license
mkdocs_mpgtheme_plugin/assets/mpgtheme/images/header-logo-placeholder.svg
mkdocs_mpgtheme_plugin/assets/mpgtheme/images/header-logo-placeholder.svg.license
mkdocs_mpgtheme_plugin/mpgtheme/partials/footer.html
mkdocs_mpgtheme_plugin/mpgtheme/partials/footer_logo.html
mkdocs_mpgtheme_plugin/mpgtheme/partials/footer_navigation.html
mkdocs_mpgtheme_plugin/mpgtheme/partials/header.html
mkdocs_mpgtheme_plugin/mpgtheme/partials/logo.html
mkdocs_mpgtheme_plugin-2025.2.12.dist-info/LICENSE.txt
mkdocs_mpgtheme_plugin-2025.2.12.dist-info/METADATA
mkdocs_mpgtheme_plugin-2025.2.12.dist-info/WHEEL
mkdocs_mpgtheme_plugin-2025.2.12.dist-info/entry_points.txt
mkdocs_mpgtheme_plugin-2025.2.12.dist-info/top_level.txt
mkdocs_mpgtheme_plugin-2025.2.12.dist-info/RECORD
