Metadata-Version: 2.2
Name: mkdocs-mpgtheme-plugin
Version: 2025.2.12
Summary: MkDocs plugin to add some MPG branding to the Material for MkDocs theme
Author-email: Thomas Breitner <mail@thms.de>
License: MIT License
Project-URL: Repository, https://github.com/tombreit/mkdocs-mpgtheme-plugin
Project-URL: Homepage, https://github.com/tombreit/mkdocs-mpgtheme-plugin
Project-URL: Documentation, https://github.com/tombreit/mkdocs-mpgtheme-plugin/blob/main/README.md
Project-URL: Issues, https://github.com/tombreit/mkdocs-mpgtheme-plugin/issues
Classifier: Framework :: MkDocs
Classifier: Topic :: Documentation
Classifier: License :: OSI Approved :: MIT License
Classifier: Programming Language :: Python :: 3
Classifier: Development Status :: 3 - Alpha
Requires-Python: >=3.9
License-File: LICENSE.txt
Requires-Dist: mkdocs>=1.6
Requires-Dist: mkdocs-material>=9.0.0
Requires-Dist: mkdocs-static-i18n>=1.3.0
Provides-Extra: dev
Requires-Dist: pre-commit; extra == "dev"
Requires-Dist: reuse; extra == "dev"
Provides-Extra: pypi
Requires-Dist: build; extra == "pypi"
Requires-Dist: twine; extra == "pypi"
